AUTHORS.rst
CONTRIBUTING.rst
HISTORY.rst
LICENSE
MANIFEST.in
README.rst
setup.cfg
setup.py
docs/API.rst
docs/Makefile
docs/authors.rst
docs/conf.py
docs/contributing.rst
docs/history.rst
docs/index.rst
docs/installation.rst
docs/make.bat
docs/readme.rst
docs/usage.rst
pyscihub/__init__.py
pyscihub/cli.py
pyscihub/pyscihub.py
pyscihub/tools.py
pyscihub.egg-info/PKG-INFO
pyscihub.egg-info/SOURCES.txt
pyscihub.egg-info/dependency_links.txt
pyscihub.egg-info/entry_points.txt
pyscihub.egg-info/not-zip-safe
pyscihub.egg-info/requires.txt
pyscihub.egg-info/top_level.txt
tests/.DS_Store
tests/__init__.py
tests/test_pyscihub.py
tests/test_tools.py
tests/.pytest_cache/.gitignore
tests/.pytest_cache/CACHEDIR.TAG
tests/.pytest_cache/README.md
tests/.pytest_cache/v/cache/lastfailed
tests/.pytest_cache/v/cache/nodeids
tests/.pytest_cache/v/cache/stepwise
tests/data/.DS_Store
tests/data/demo_pdfs/.DS_Store
tests/data/demo_pdfs/cruz-f-subramanian-a-bruck-b-p-iori-m-2017-a-heuristic-algorithm-for-a-single-vehicle-static-bike-sharing-rebalancing-problem-computers-operations-research-79-1933-doi101016jcor201609025.pdf
tests/data/demo_pdfs/forbes-h-stark-a-m-hopkins-s-w-fireman-g-d-2019-the-effects-of-group-membership-on-college-students-social-exclusion-of-peers-and-bystander-behavior-the-journal-of-psychology-123-doi1010800022398020191642839.pdf
tests/data/demo_pdfs/pdf_paths.csv