Metadata-Version: 2.1
Name: pyscihub
Version: 0.1.2
Summary: Command-line and Python API to download PDFs directly from Sci-Hub
Home-page: https://github.com/markkvdb/pyscihub
Author: Mark van der Broek
Author-email: markvanderbroek@gmail.com
License: MIT license
Keywords: pyscihub
Platform: UNKNOWN
Classifier: Development Status :: 3 - Alpha
Classifier: Intended Audience :: Developers
Classifier: License :: OSI Approved :: MIT License
Classifier: Natural Language :: English
Classifier: Programming Language :: Python :: 3
Classifier: Programming Language :: Python :: 3.8
Requires-Python: >=3.8
